{"name":"Python-couchdblogger","tagline":"Python CouchDB logging handler","body":"python-couchdblogger\r\n====================\r\n\r\nTests adn requirements:\r\n-----------------------\r\n\r\n[![Build Status](https://drone.io/github.com/FedeG/python-couchdblogger/status.png)](https://drone.io/github.com/FedeG/python-couchdblogger/latest) [![Requirements Status](https://requires.io/github/FedeG/python-couchdblogger/requirements.svg?branch=master)](https://requires.io/github/FedeG/python-couchdblogger/requirements/?branch=master)\r\n\r\nDocumentation:\r\n--------------\r\n\r\nSimple module for logging to CouchDB. \r\nProbably not best choise for logging backend, because CouchDB is not good with massive write operations. \r\n\r\n    https://pypi.python.org/pypi/couchdblogger\r\n\r\nUsage:\r\n\r\n    import couchdblogger\r\n\r\n    logger = logging.getLogger('mylogger')\r\n    logger.setLevel('ERROR')\r\n    logger.addHandler(couchdblogger.CouchDBLogHandler())\r\n   \r\nUsage with ssl:\r\n\r\n    import couchdblogger\r\n\r\n    logger = logging.getLogger('mylogger')\r\n    logger.setLevel('ERROR')\r\n    logger.addHandler(couchdblogger.CouchDBLogHandler(ssl=True, request_args={\"verify\": True}))\r\n\r\nScript to run tests:\r\n--------------------\r\n\r\n1- Install:\r\n\r\n    python setup.py install\r\n    pip install mock\r\n    pip install nose\r\n\r\n2- Run tests:\r\n\r\n    python setup.py test\r\n\r\n  or:\r\n\r\n    nosetests -vv\r\n\r\nRun nosetests with coverage:\r\n\r\n    nosetests --with-coverage; coverage report\r\n","google":"","note":"Don't delete this file! It's used internally to help with page regeneration."}